AUTHORS
BUGS.md
CHANGES.rst
LICENSE
MANIFEST.in
README.rst
TODO.md
setup.py
docs/Makefile
docs/api.rst
docs/api_benchmark_io_refbased_fits.rst
docs/api_benchmark_metrics_refbased.rst
docs/api_io_fits.rst
docs/api_io_images.rst
docs/api_io_pil.rst
docs/api_io_plot.rst
docs/api_optimization_bruteforce.rst
docs/api_optimization_differential_evolution.rst
docs/api_optimization_objectivefunc_wavelets_mrfilter_delta_psi.rst
docs/api_optimization_saes.rst
docs/api_processing_filtering_hard_filter.rst
docs/api_processing_filtering_pixel_clusters.rst
docs/api_processing_transform_mrtransform.rst
docs/api_processing_transform_starlet.rst
docs/api_ui_argparse.rst
docs/api_ui_commons.rst
docs/api_ui_filter_with_mrfilter.rst
docs/api_ui_filter_with_mrtransform.rst
docs/api_ui_filter_with_starlet.rst
docs/conf.py
docs/developer.rst
docs/index.rst
docs/init_sphinx.sh
docs/intro.rst
docs/logo_asterics.png
docs/logo_cea.png
docs/logo_irfu.png
docs/logo_univearths.jpeg
docs/make.bat
docs/_static/.empty
examples/plot_optim_bruteforce.py
examples/plot_optim_differential_evolution.py
examples/plot_optim_saes.py
examples/plot_pywi_starlet.py
examples/plot_starlet_denoising.py
pywi/__init__.py
pywi.egg-info/PKG-INFO
pywi.egg-info/SOURCES.txt
pywi.egg-info/dependency_links.txt
pywi.egg-info/entry_points.txt
pywi.egg-info/requires.txt
pywi.egg-info/top_level.txt
pywi/benchmark/__init__.py
pywi/benchmark/core.py
pywi/benchmark/io/__init__.py
pywi/benchmark/io/refbased/__init__.py
pywi/benchmark/io/refbased/fits.py
pywi/benchmark/metrics/__init__.py
pywi/benchmark/metrics/refbased.py
pywi/benchmark/ui/__init__.py
pywi/benchmark/ui/argparse_commons.py
pywi/benchmark/ui/filter_with_mrfilter.py
pywi/benchmark/ui/filter_with_mrtransform.py
pywi/data/__init__.py
pywi/data/galaxy.npy
pywi/io/__init__.py
pywi/io/fits.py
pywi/io/images.py
pywi/io/pil.py
pywi/io/plot.py
pywi/optimization/__init__.py
pywi/optimization/objectivefunc/__init__.py
pywi/optimization/objectivefunc/wavelets_mrfilter_delta_psi.py
pywi/processing/__init__.py
pywi/processing/compositing/__init__.py
pywi/processing/compositing/filter_with_mrfilter.py
