Metadata-Version: 1.2
Name: pywi
Version: 0.3.dev12
Summary: Python Wavelet Imaging
Home-page: https://github.com/jeremiedecock/pywi
Author: Jeremie DECOCK
Author-email: jd.jdhp@gmail.com
Maintainer: Jeremie DECOCK
Maintainer-email: jd.jdhp@gmail.com
License: UNKNOWN
Download-URL: https://github.com/jeremiedecock/pywi
Keywords: multiresolution image filter wavelet
Platform: UNKNOWN
Classifier: Development Status :: 4 - Beta
Classifier: Intended Audience :: Developers
Classifier: License :: OSI Approved :: MIT License
Classifier: Natural Language :: English
Classifier: Operating System :: OS Independent
Classifier: Programming Language :: Python :: 3
Classifier: Topic :: Software Development :: Libraries
Classifier: Topic :: Software Development :: Libraries :: Python Modules
Classifier: Topic :: Software Development :: Libraries :: Application Frameworks
